[{"label":"Definition","autoid":"Definition*-4.1","refnum":"??","reftag":"","title":"","reflabel":"Definition","cls":"Definition","file":"lecture_4","neu":true,"id":"Definition*-4.1"},{"label":"Theorem","autoid":"Theorem*-4.2","refnum":"??","reftag":"","title":"","reflabel":"Theorem","cls":"Theorem","file":"lecture_4","neu":true,"id":"Theorem*-4.2"},{"label":"Theorem","autoid":"Theorem*-4.3","refnum":"??","reftag":"","title":"","reflabel":"Theorem","cls":"Theorem","file":"lecture_4","neu":true,"id":"Theorem*-4.3"},{"label":"Definition","autoid":"Definition*-5.1","refnum":"??","reftag":"","title":"","reflabel":"Definition","cls":"Definition","file":"lecture_4","neu":true,"id":"Definition*-5.1"},{"label":"Theorem","autoid":"Theorem*-5.2","refnum":"??","reftag":"","title":"","reflabel":"Theorem","cls":"Theorem","file":"lecture_4","neu":true,"id":"Theorem*-5.2"},{"label":"Theorem","autoid":"Theorem*-5.3","refnum":"??","reftag":"","title":"","reflabel":"Theorem","cls":"Theorem","file":"lecture_4","neu":true,"id":"Theorem*-5.3"},{"label":"Question","id":"Question*-5.1","refnum":"??","reftag":"","title":"","reflabel":"Question","cls":"Question","file":"lecture_4","neu":true,"autoid":"Question*-5.1"},{"label":"Definition","id":"Definition*-6.1","refnum":"??","reftag":"","title":"","reflabel":"Definition","cls":"Definition","file":"lecture_4","neu":true,"autoid":"Definition*-6.1"},{"label":"Definition","id":"Definition*-6.2","refnum":"??","reftag":"","title":"","reflabel":"Definition","cls":"Definition","file":"lecture_4","neu":true,"autoid":"Definition*-6.2"},{"label":"Theorem","id":"Theorem*-6.3","refnum":"??","reftag":"","title":"","reflabel":"Theorem","cls":"Theorem","file":"lecture_4","neu":true,"autoid":"Theorem*-6.3"},{"label":"Definition","autoid":"Definition*-8.1","refnum":"??","reftag":"","title":"","reflabel":"Definition","cls":"Definition","file":"lecture_4","neu":true,"id":"Definition*-8.1"},{"label":"Theorem","autoid":"Theorem*-8.2","refnum":"??","reftag":"","title":"","reflabel":"Theorem","cls":"Theorem","file":"lecture_4","neu":true,"id":"Theorem*-8.2"},{"label":"Theorem","autoid":"Theorem*-8.3","refnum":"??","reftag":"","title":"","reflabel":"Theorem","cls":"Theorem","file":"lecture_4","neu":true,"id":"Theorem*-8.3"}]