[{"reftag":"","file":"lecture_5","autoid":"Definition*-4.1","label":"Definition","neu":true,"refnum":"??","cls":"Definition","title":"","id":"Definition*-4.1","reflabel":"Definition"},{"reftag":"","file":"lecture_5","autoid":"Theorem*-4.2","label":"Theorem","neu":true,"refnum":"??","cls":"Theorem","title":"","id":"Theorem*-4.2","reflabel":"Theorem"},{"reftag":"","file":"lecture_5","autoid":"Theorem*-4.3","label":"Theorem","neu":true,"refnum":"??","cls":"Theorem","title":"","id":"Theorem*-4.3","reflabel":"Theorem"},{"reftag":"","file":"lecture_5","autoid":"Question*-1.1","cls":"Question","neu":true,"refnum":"??","title":"","label":"Question","id":"Question*-1.1","reflabel":"Question"},{"reftag":"","file":"lecture_5","autoid":"Definition*-2.1","cls":"Definition","neu":true,"refnum":"??","title":"","label":"Definition","id":"Definition*-2.1","reflabel":"Definition"},{"reftag":"","file":"lecture_5","autoid":"Theorem*-2.2","cls":"Theorem","neu":true,"refnum":"??","title":"","label":"Theorem","id":"Theorem*-2.2","reflabel":"Theorem"},{"reftag":"","file":"lecture_5","autoid":"Theorem*-2.3","cls":"Theorem","neu":true,"refnum":"??","title":"","label":"Theorem","id":"Theorem*-2.3","reflabel":"Theorem"}]